reparsec/__init__.py
reparsec/core/__init__.py
reparsec/core/chain.py
reparsec/core/combinators.py
reparsec/core/layout.py
reparsec/core/parser.py
reparsec/core/primitive.py
reparsec/core/recovery.py
reparsec/core/repair.py
reparsec/core/result.py
reparsec/core/scannerless.py
reparsec/core/sequence.py
reparsec/core/stream.py
reparsec/core/types.py
reparsec/layout.py
reparsec/lexer.py
reparsec/parser.py
reparsec/primitive.py
reparsec/py.typed
reparsec/scannerless.py
reparsec/sequence.py
reparsec/types.py
reparsec-0.4.3.dist-info/LICENSE
reparsec-0.4.3.dist-info/METADATA
reparsec-0.4.3.dist-info/WHEEL
reparsec-0.4.3.dist-info/RECORD
