Metadata-Version: 2.1
Name: reparsec
Version: 0.4.3
Summary: Parser
Home-page: https://github.com/ethframe/reparsec
License: MIT
Author: ethframe
Author-email: ethframe@gmail.com
Requires-Python: >=3.7,<4.0
Classifier: Development Status :: 4 - Beta
Classifier: License :: OSI Approved :: MIT License
Classifier: Programming Language :: Python :: 3
Classifier: Programming Language :: Python :: 3.7
Classifier: Programming Language :: Python :: 3.8
Classifier: Programming Language :: Python :: 3.9
Classifier: Programming Language :: Python :: 3.10
Classifier: Programming Language :: Python :: 3.11
Classifier: Typing :: Typed
Requires-Dist: typing-extensions (>=4.1,<5.0)
Project-URL: Documentation, https://reparsec.readthedocs.io/
Project-URL: Repository, https://github.com/ethframe/reparsec
